.DS_Store
PyJPString-0.0.3.dist-info/DESCRIPTION.rst
PyJPString-0.0.3.dist-info/METADATA
PyJPString-0.0.3.dist-info/RECORD
PyJPString-0.0.3.dist-info/WHEEL
PyJPString-0.0.3.dist-info/metadata.json
PyJPString-0.0.3.dist-info/top_level.txt
jpstring/__init__.py
jpstring/converters.py
jpstring/normalizers.py
jpstring/patterns.py
jpstring/string.py
jpstring/validators.py
jpstring/django/__init__.py
jpstring/django/validators.py
