Metadata-Version: 2.0
Name: PyJPString
Version: 0.0.3
Summary: Python japanese string utilities.
Home-page: http://github.com/odoku/PyJPString
Author: odoku
Author-email: masashi.onogawa@wamw.jp
License: MIT
Keywords: japanese,string
Platform: UNKNOWN
Requires-Dist: six (>=1.10.0)
Requires-Dist: zenhan (>=0.5.2)
Provides-Extra: test
Requires-Dist: django; extra == 'test'
Requires-Dist: pytest (==2.9.1); extra == 'test'
